dissect/database/__init__.py
dissect/database/exception.py
dissect/database/bsd/__init__.py
dissect/database/bsd/c_db.py
dissect/database/bsd/c_db.pyi
dissect/database/bsd/db.py
dissect/database/bsd/tools/__init__.py
dissect/database/bsd/tools/c_rpm.py
dissect/database/bsd/tools/c_rpm.pyi
dissect/database/bsd/tools/rpm.py
dissect/database/ese/__init__.py
dissect/database/ese/btree.py
dissect/database/ese/c_ese.py
dissect/database/ese/c_ese.pyi
dissect/database/ese/compression.py
dissect/database/ese/cursor.py
dissect/database/ese/ese.py
dissect/database/ese/exception.py
dissect/database/ese/index.py
dissect/database/ese/lcmapstring.py
dissect/database/ese/page.py
dissect/database/ese/record.py
dissect/database/ese/sorting_table.py
dissect/database/ese/table.py
dissect/database/ese/util.py
dissect/database/ese/ntds/__init__.py
dissect/database/ese/ntds/c_ds.py
dissect/database/ese/ntds/c_ds.pyi
dissect/database/ese/ntds/c_pek.py
dissect/database/ese/ntds/c_pek.pyi
dissect/database/ese/ntds/c_sd.py
dissect/database/ese/ntds/c_sd.pyi
dissect/database/ese/ntds/database.py
dissect/database/ese/ntds/ntds.py
dissect/database/ese/ntds/pek.py
dissect/database/ese/ntds/query.py
dissect/database/ese/ntds/schema.py
dissect/database/ese/ntds/sd.py
dissect/database/ese/ntds/util.py
dissect/database/ese/ntds/objects/__init__.py
dissect/database/ese/ntds/objects/applicationsettings.py
dissect/database/ese/ntds/objects/attributeschema.py
dissect/database/ese/ntds/objects/builtindomain.py
dissect/database/ese/ntds/objects/certificationauthority.py
dissect/database/ese/ntds/objects/classschema.py
dissect/database/ese/ntds/objects/classstore.py
dissect/database/ese/ntds/objects/computer.py
dissect/database/ese/ntds/objects/configuration.py
dissect/database/ese/ntds/objects/container.py
dissect/database/ese/ntds/objects/controlaccessright.py
dissect/database/ese/ntds/objects/crldistributionpoint.py
dissect/database/ese/ntds/objects/crossref.py
dissect_database-1.1.dev4.dist-info/licenses/COPYRIGHT
dissect_database-1.1.dev4.dist-info/licenses/LICENSE
dissect_database-1.1.dev4.dist-info/METADATA
dissect_database-1.1.dev4.dist-info/WHEEL
dissect_database-1.1.dev4.dist-info/top_level.txt
dissect_database-1.1.dev4.dist-info/RECORD
