Metadata-Version: 2.4
Name: dissect.database
Version: 1.1.dev4
Summary: A Dissect module implementing parsers for various database formats, including Berkeley DB, Microsofts Extensible Storage Engine (ESE) and SQLite3
Author-email: Dissect Team <dissect@fox-it.com>
License-Expression: Apache-2.0
Project-URL: homepage, https://dissect.tools
Project-URL: documentation, https://docs.dissect.tools/en/latest/projects/dissect.database
Project-URL: repository, https://github.com/fox-it/dissect.database
Classifier: Development Status :: 5 - Production/Stable
Classifier: Environment :: Console
Classifier: Intended Audience :: Developers
Classifier: Intended Audience :: Information Technology
Classifier: Operating System :: OS Independent
Classifier: Programming Language :: Python :: 3
Classifier: Topic :: Internet :: Log Analysis
Classifier: Topic :: Scientific/Engineering :: Information Analysis
Classifier: Topic :: Security
Classifier: Topic :: Utilities
Requires-Python: >=3.10
License-File: LICENSE
License-File: COPYRIGHT
Requires-Dist: dissect.cstruct<5,>=4
Requires-Dist: dissect.util<4,>=3.24.dev1
Provides-Extra: full
Requires-Dist: pycryptodome; extra == "full"
Provides-Extra: dev
Requires-Dist: dissect.database[full]; extra == "dev"
Requires-Dist: dissect.cstruct<5.0.dev,>=4.0.dev; extra == "dev"
Requires-Dist: dissect.util<4.0.dev,>=3.24.dev; extra == "dev"
Dynamic: license-file
